{
  "display": {
    "fontFamily": {
      "value": "Noto Serif",
      "type": "text"
    },
    "fontWeight": {
      "default": {
        "value": "Regular",
        "type": "text"
      },
      "heavy": {
        "value": "Bold",
        "type": "text"
      }
    }
  },
  "heading": {
    "fontFamily": {
      "value": "Noto Sans",
      "type": "text"
    },
    "fontWeight": {
      "default": {
        "value": "Regular",
        "type": "text"
      },
      "heavy": {
        "value": "Bold",
        "type": "text"
      }
    }
  },
  "bodycopy": {
    "fontFamily": {
      "value": "Open Sans",
      "type": "text"
    },
    "fontWeight": {
      "default": {
        "value": "Regular",
        "type": "text"
      },
      "heavy": {
        "value": "Bold",
        "type": "text"
      }
    }
  }
}